docs/demo/demo-decorator.py
docs/demo/demo-tree.py
docs/demo/demo.py
docs/demo/livekey.py
docs/demo/run-demo1.py
docs/example/autocomplete-demo.py
docs/example/cheatsheet.py
docs/example/completers.py
docs/example/helpme.py
docs/example/many-args.py
docs/example/multi-parameters.py
docs/example/multiapp.py
docs/example/nukefile.py
docs/example/pos-args.py
docs/example/quickstart.py
docs/example/subcommands.py
docs/example/sublog-demo.py
docs/example/sublog-formatter.py
docs/example/sublog-init.py
nuclear/__init__.py
nuclear/py.typed
nuclear/version.py
nuclear/cli/__init__.py
nuclear/cli/help.py
nuclear/cli/args/__init__.py
nuclear/cli/args/args_que.py
nuclear/cli/args/container.py
nuclear/cli/autocomplete/__init__.py
nuclear/cli/autocomplete/autocomplete.py
nuclear/cli/autocomplete/install.py
nuclear/cli/builder/__init__.py
nuclear/cli/builder/builder.py
nuclear/cli/builder/decorator_builder.py
nuclear/cli/builder/rule.py
nuclear/cli/builder/rule_factory.py
nuclear/cli/builder/typedef.py
nuclear/cli/completers/__init__.py
nuclear/cli/completers/file.py
nuclear/cli/parser/__init__.py
nuclear/cli/parser/context.py
nuclear/cli/parser/error.py
nuclear/cli/parser/inject.py
nuclear/cli/parser/internal_vars.py
nuclear/cli/parser/keyword.py
nuclear/cli/parser/matcher.py
nuclear/cli/parser/parser.py
nuclear/cli/parser/transform.py
nuclear/cli/parser/validate.py
nuclear/cli/parser/value.py
nuclear/cli/types/__init__.py
nuclear/cli/types/boolean.py
nuclear/cli/types/filesystem.py
nuclear/cli/types/time.py
nuclear/nuke/__init__.py
nuclear/nuke/cli.py
nuclear/nuke/config.py
nuclear/nuke/invoke.py
nuclear/nuke/paths.py
nuclear/nuke/shell.py
nuclear/shell/__init__.py
nuclear/shell/background_cmd.py
nuclear/shell/shell_utils.py
nuclear/sublog/__init__.py
nuclear/sublog/catch.py
nuclear/sublog/context_error.py
nuclear/sublog/exception.py
nuclear/sublog/logging.py
nuclear/utils/__init__.py
nuclear/utils/collections.py
nuclear/utils/config.py
nuclear/utils/datamodel.py
nuclear-2.7.0.dist-info/licenses/LICENSE
nuclear-2.7.0.dist-info/METADATA
nuclear-2.7.0.dist-info/WHEEL
nuclear-2.7.0.dist-info/entry_points.txt
nuclear-2.7.0.dist-info/top_level.txt
nuclear-2.7.0.dist-info/RECORD
