Metadata-Version: 2.4
Name: nuclear
Version: 2.7.0
Summary: Declarative parser for command line interfaces
Author-email: igrek51 <igrek51.dev@gmail.com>
License: MIT
Project-URL: Homepage, https://github.com/igrek51/nuclear
Project-URL: Repository, https://github.com/igrek51/nuclear.git
Project-URL: Documentation, https://igrek51.github.io/nuclear
Project-URL: Read the Docs, https://nuclear-py.readthedocs.io
Classifier: Programming Language :: Python :: 3
Classifier: Programming Language :: Python :: 3.10
Classifier: Programming Language :: Python :: 3.11
Classifier: Programming Language :: Python :: 3.12
Classifier: License :: OSI Approved :: MIT License
Classifier: Operating System :: OS Independent
Requires-Python: >=3.10.0
License-File: LICENSE
Requires-Dist: PyYAML>=6.0
Provides-Extra: dev
Requires-Dist: build==1.0.0; extra == "dev"
Requires-Dist: pytest==8.2.2; extra == "dev"
Requires-Dist: mock==4.0.3; extra == "dev"
Requires-Dist: coverage[toml]==6.3.2; extra == "dev"
Requires-Dist: setuptools==70.0.0; extra == "dev"
Requires-Dist: twine==4.0.0; extra == "dev"
Requires-Dist: wheel==0.38.4; extra == "dev"
Requires-Dist: mkdocs==1.4.0; extra == "dev"
Requires-Dist: mkdocs-material==8.5.6; extra == "dev"
Requires-Dist: backoff==2.0.1; extra == "dev"
Requires-Dist: pydantic==2.4.0; extra == "dev"
Requires-Dist: mypy==1.10.1; extra == "dev"
Requires-Dist: types-PyYAML==6.0.12.20240311; extra == "dev"
Dynamic: license-file
